gsply/__init__.py
gsply/formats.py
gsply/gsdata.py
gsply/py.typed
gsply/reader.py
gsply/sog_reader.py
gsply/utils.py
gsply/writer.py
gsply/torch/__init__.py
gsply/torch/compression.py
gsply/torch/gstensor.py
gsply/torch/io.py
gsply-0.2.13.dist-info/licenses/LICENSE
gsply-0.2.13.dist-info/METADATA
gsply-0.2.13.dist-info/WHEEL
gsply-0.2.13.dist-info/top_level.txt
gsply-0.2.13.dist-info/zip-safe
gsply-0.2.13.dist-info/RECORD
