Metadata-Version: 2.4
Name: gsply
Version: 0.2.13
Summary: Ultra-fast Gaussian Splatting PLY I/O library - pure Python with NumPy and Numba. Features 11x faster GPU transfers and automatic format state tracking for seamless conversions.
Author-email: OpsiClear <yehe@opsiclear.com>
Maintainer-email: OpsiClear <yehe@opsiclear.com>
License-Expression: MIT
Project-URL: Homepage, https://github.com/OpsiClear/gsply
Project-URL: Repository, https://github.com/OpsiClear/gsply
Project-URL: Issues, https://github.com/OpsiClear/gsply/issues
Project-URL: Documentation, https://github.com/OpsiClear/gsply#readme
Keywords: gaussian-splatting,ply,3d,point-cloud,compression,nerf,3dgs
Classifier: Development Status :: 4 - Beta
Classifier: Intended Audience :: Developers
Classifier: Intended Audience :: Science/Research
Classifier: Programming Language :: Python :: 3
Classifier: Programming Language :: Python :: 3.10
Classifier: Programming Language :: Python :: 3.11
Classifier: Programming Language :: Python :: 3.12
Classifier: Programming Language :: Python :: 3.13
Classifier: Topic :: Scientific/Engineering
Classifier: Topic :: Multimedia :: Graphics :: 3D Modeling
Classifier: Topic :: Software Development :: Libraries :: Python Modules
Classifier: Operating System :: OS Independent
Requires-Python: >=3.10
License-File: LICENSE
Requires-Dist: numpy>=1.20.0
Requires-Dist: numba>=0.59.0
Provides-Extra: sogs
Requires-Dist: imagecodecs>=2024.0.0; extra == "sogs"
Provides-Extra: dev
Requires-Dist: pytest>=7.0; extra == "dev"
Requires-Dist: pytest-cov; extra == "dev"
Requires-Dist: build; extra == "dev"
Requires-Dist: twine; extra == "dev"
Requires-Dist: mypy>=1.0; extra == "dev"
Requires-Dist: ruff>=0.1.0; extra == "dev"
Requires-Dist: pre-commit>=3.0.0; extra == "dev"
Provides-Extra: benchmark
Requires-Dist: open3d>=0.17.0; extra == "benchmark"
Requires-Dist: plyfile>=0.9.0; extra == "benchmark"
Provides-Extra: docs
Requires-Dist: sphinx>=7.2; extra == "docs"
Requires-Dist: myst-parser>=2.0; extra == "docs"
Requires-Dist: furo>=2024.0.0; extra == "docs"
Requires-Dist: sphinx-autodoc-typehints>=2.0; extra == "docs"
Provides-Extra: all
Requires-Dist: imagecodecs>=2024.0.0; extra == "all"
Requires-Dist: pytest>=7.0; extra == "all"
Requires-Dist: pytest-cov; extra == "all"
Requires-Dist: build; extra == "all"
Requires-Dist: twine; extra == "all"
Requires-Dist: open3d>=0.17.0; extra == "all"
Requires-Dist: plyfile>=0.9.0; extra == "all"
Requires-Dist: sphinx>=7.2; extra == "all"
Requires-Dist: myst-parser>=2.0; extra == "all"
Requires-Dist: furo>=2024.0.0; extra == "all"
Requires-Dist: sphinx-autodoc-typehints>=2.0; extra == "all"
Dynamic: license-file
